fracture_detector/__init__.py
fracture_detector/utils.py
FractureDetector-0.0.11.dist-info/LICENSE.txt
FractureDetector-0.0.11.dist-info/METADATA
FractureDetector-0.0.11.dist-info/WHEEL
FractureDetector-0.0.11.dist-info/top_level.txt
FractureDetector-0.0.11.dist-info/RECORD
